octopose/__init__.py
octopose/__main__.py
octopose/__version__.py
octopose/config.py
octopose/deploy.py
octopose/generate_manifest.py
octopose/local_deploy.py
octopose/nu.py
octopose/octo.py
octopose/octopose.py
octopose/remote_deploy.py
octopose/subprocess_runner.py
octopose/third_party/NuGet.exe
octopose-0.2.14.dist-info/LICENSE
octopose-0.2.14.dist-info/METADATA
octopose-0.2.14.dist-info/WHEEL
octopose-0.2.14.dist-info/entry_points.txt
octopose-0.2.14.dist-info/top_level.txt
octopose-0.2.14.dist-info/RECORD
