Metadata-Version: 2.1
Name: octopose
Version: 0.2.14
Summary: Command line tools for managing local and remote octopus deploys using manifests.
Home-page: https://github.com/HuddleEng/octopose
Author: Huddleoss
Author-email: opensource@huddle.com
License: MIT
Platform: UNKNOWN
Classifier: Intended Audience :: Developers
Classifier: License :: OSI Approved :: MIT License
Classifier: Programming Language :: Python
Classifier: Programming Language :: Python :: 3.7
Requires-Python: >=3.7.0
Requires-Dist: requests (>=2.22.0)
Requires-Dist: pyyaml (>=5.3)
